README.md
setup.py
bin/ditio
ditio/__init__.py
ditio/cmd.py
ditio/site.py
ditio/system.py
ditio/utils.py
ditio.egg-info/PKG-INFO
ditio.egg-info/SOURCES.txt
ditio.egg-info/dependency_links.txt
ditio.egg-info/top_level.txt
ditio/notebook/__init__.py
ditio/notebook/code.py
ditio/notebook/language.py
ditio/notebook/markdown.py