Metadata-Version: 1.0
Name: ditio
Version: 0.0.2.4
Summary: Publish articles
Home-page: UNKNOWN
Author: thinkersilver
Author-email: myonlineprofile2012@gmail.com
License: UNKNOWN
Platform: UNKNOWN
